odoo/addons/mail_server_relay_disallowed/README.rst
odoo/addons/mail_server_relay_disallowed/__init__.py
odoo/addons/mail_server_relay_disallowed/__manifest__.py
odoo/addons/mail_server_relay_disallowed/i18n/mail_server_relay_disallowed.pot
odoo/addons/mail_server_relay_disallowed/models/__init__.py
odoo/addons/mail_server_relay_disallowed/models/ir_mail_server.py
odoo/addons/mail_server_relay_disallowed/readme/CONTRIBUTORS.rst
odoo/addons/mail_server_relay_disallowed/readme/DESCRIPTION.rst
odoo/addons/mail_server_relay_disallowed/readme/USAGE.rst
odoo/addons/mail_server_relay_disallowed/static/description/icon.png
odoo/addons/mail_server_relay_disallowed/static/description/index.html
odoo13_addon_mail_server_relay_disallowed-13.0.1.0.1.dist-info/METADATA
odoo13_addon_mail_server_relay_disallowed-13.0.1.0.1.dist-info/WHEEL
odoo13_addon_mail_server_relay_disallowed-13.0.1.0.1.dist-info/top_level.txt
odoo13_addon_mail_server_relay_disallowed-13.0.1.0.1.dist-info/RECORD
